CHANGELOG.md
LICENSE
MANIFEST.in
README.rst
setup.cfg
setup.py
tests/__init__.py
tests/test_blocks.py
tests/test_decorators.py
tests/test_fields.py
tests/test_forms.py
tests/test_validators.py
tests/test_wagtail_hooks.py
tests/test_widgets.py
tests/testapp/__init__.py
tests/testapp/manage.py
tests/testapp/home/__init__.py
tests/testapp/home/decorators.py
tests/testapp/home/models.py
tests/testapp/home/wagtail_hooks.py
tests/testapp/home/migrations/0001_initial.py
tests/testapp/home/migrations/0002_create_homepage.py
tests/testapp/home/migrations/0003_homepage_body.py
tests/testapp/home/migrations/__init__.py
tests/testapp/home/templatetags/__init__.py
tests/testapp/home/templatetags/pretty_tags.py
tests/testapp/testapp/__init__.py
tests/testapp/testapp/settings.py
tests/testapp/testapp/urls.py
tests/testapp/testapp/wsgi.py
tests/testapp/testapp/grains/__init__.py
tests/testapp/testapp/grains/rich_text.py
wagtaildraftail/__init__.py
wagtaildraftail/blocks.py
wagtaildraftail/decorators.py
wagtaildraftail/draft_text.py
wagtaildraftail/fields.py
wagtaildraftail/forms.py
wagtaildraftail/utils.py
wagtaildraftail/validators.py
wagtaildraftail/wagtail_hooks.py
wagtaildraftail/widgets.py
wagtaildraftail.egg-info/PKG-INFO
wagtaildraftail.egg-info/SOURCES.txt
wagtaildraftail.egg-info/dependency_links.txt
wagtaildraftail.egg-info/not-zip-safe
wagtaildraftail.egg-info/pbr.json
wagtaildraftail.egg-info/requires.txt
wagtaildraftail.egg-info/top_level.txt
wagtaildraftail/client/registry.js
wagtaildraftail/client/wagtaildraftail.js
wagtaildraftail/client/wagtaildraftail.scss
wagtaildraftail/client/wagtaildraftail.test.js
wagtaildraftail/client/webpack.config.dev.js
wagtaildraftail/client/webpack.config.prod.js
wagtaildraftail/client/decorators/Document.js
wagtaildraftail/client/decorators/Document.test.js
wagtaildraftail/client/decorators/Link.js
wagtaildraftail/client/decorators/Link.test.js
wagtaildraftail/client/decorators/index.js
wagtaildraftail/client/decorators/index.test.js
wagtaildraftail/client/decorators/__snapshots__/Document.test.js.snap
wagtaildraftail/client/decorators/__snapshots__/Link.test.js.snap
wagtaildraftail/client/sources/.DS_Store
wagtaildraftail/client/sources/DocumentSource.js
